bqseine/.agent.py.swo
bqseine/.agent.py.swp
bqseine/__init__.py
bqseine/agent.py
bqseine/polyp.py
bqseine-1.1.3.dist-info/METADATA
bqseine-1.1.3.dist-info/WHEEL
bqseine-1.1.3.dist-info/licenses/LICENSE
bqseine-1.1.3.dist-info/RECORD
