Metadata-Version: 2.4
Name: bqseine
Version: 1.1.3
Summary: ETL for BigQuery
Project-URL: Homepage, https://github.com/shaafiee/seine
Project-URL: Issues, https://github.com/shaafiee/siene/issues
Author-email: Shaafiee <shaafiee@gmail.com>
License-Expression: MIT
License-File: LICENSE
Classifier: Operating System :: OS Independent
Classifier: Programming Language :: Python :: 3
Requires-Python: >=3.9
